cheq_rti_wsgi_middleware/RtiWsgiMiddleware.py
cheq_rti_wsgi_middleware/__init__.py
cheq_rti_wsgi_middleware/constants/__init__.py
cheq_rti_wsgi_middleware/constants/errors.py
cheq_rti_wsgi_middleware/constants/rti_constants.py
cheq_rti_wsgi_middleware/examples/__init__.py
cheq_rti_wsgi_middleware/examples/django_wsgi_app.py
cheq_rti_wsgi_middleware/examples/flask_wsgi_app.py
cheq_rti_wsgi_middleware/utils/__init__.py
cheq_rti_wsgi_middleware/utils/logger.py
cheq_rti_wsgi_middleware/utils/request_builder.py
tests/__init__.py
tests/test_rti_options.py
cheq_rti_wsgi_middleware-1.0.5.dist-info/LICENSE
cheq_rti_wsgi_middleware-1.0.5.dist-info/METADATA
cheq_rti_wsgi_middleware-1.0.5.dist-info/WHEEL
cheq_rti_wsgi_middleware-1.0.5.dist-info/top_level.txt
cheq_rti_wsgi_middleware-1.0.5.dist-info/RECORD
