Metadata-Version: 2.1
Name: cheq_rti_wsgi_middleware
Version: 1.0.5
Summary: cheq middlewares for wsgi application
Home-page: https://github.com/cheq-ai/Cheq-Python-Middlewares
Author: CHEQ.AI
Classifier: Programming Language :: Python :: 3
Classifier: License :: OSI Approved :: MIT License
Classifier: Operating System :: OS Independent
Requires-Python: >=3.9
License-File: LICENSE
